pyaccelerator/__init__.py
pyaccelerator/accelerators.py
pyaccelerator/beam.py
pyaccelerator/constraints.py
pyaccelerator/elements/__init__.py
pyaccelerator/elements/base.py
pyaccelerator/elements/custom.py
pyaccelerator/elements/dipole.py
pyaccelerator/elements/drift.py
pyaccelerator/elements/kicker.py
pyaccelerator/elements/quadrupole.py
pyaccelerator/elements/sextupole.py
pyaccelerator/elements/utils.py
pyaccelerator/harmonic_analysis.py
pyaccelerator/lattice.py
pyaccelerator/sampling.py
pyaccelerator/transfer_matrix.py
pyaccelerator/utils.py
pyaccelerator-0.2.0.dist-info/LICENSE
pyaccelerator-0.2.0.dist-info/METADATA
pyaccelerator-0.2.0.dist-info/WHEEL
pyaccelerator-0.2.0.dist-info/RECORD
