Metadata-Version: 2.1
Name: pyaccelerator
Version: 0.2.0
Summary: Accelerator building blocks.
Home-page: https://github.com/loiccoyle/pyaccelerator
License: MIT
Author: Loic Coyle
Author-email: loic.coyle <loic.coyle@hotmail.fr
Requires-Python: >=3.9,<4.0
Classifier: License :: OSI Approved :: MIT License
Classifier: Programming Language :: Python :: 3
Classifier: Programming Language :: Python :: 3.9
Classifier: Programming Language :: Python :: 3.10
Classifier: Programming Language :: Python :: 3.11
Classifier: Programming Language :: Python :: 3.12
Provides-Extra: docs
Requires-Dist: matplotlib (>=3.1.0,<4.0.0)
Requires-Dist: numpy (>=2.0.0,<3.0.0)
Requires-Dist: scipy (>=1.5.2,<2.0.0)
Project-URL: Repository, https://github.com/loiccoyle/pyaccelerator
